[
  {
    "ContainingType": "nbRecruitment.Controllers.CandidateController",
    "Method": "availableTransfer",
    "RelativePath": "api/Candidate/availableTransfer",
    "HttpMethod": "GET",
    "IsController": true,
    "Order": 0,
    "Parameters": [],
    "ReturnTypes": []
  },
  {
    "ContainingType": "nbRecruitment.Controllers.CandidateController",
    "Method": "emailCandidate",
    "RelativePath": "api/Candidate/emailCandidate",
    "HttpMethod": "POST",
    "IsController": true,
    "Order": 0,
    "Parameters": [
      {
        "Name": "candidateEmail",
        "Type": "System.String",
        "IsRequired": false
      },
      {
        "Name": "JobType",
        "Type": "System.String",
        "IsRequired": false
      },
      {
        "Name": "link",
        "Type": "System.String",
        "IsRequired": false
      }
    ],
    "ReturnTypes": []
  },
  {
    "ContainingType": "nbRecruitment.Controllers.CandidateController",
    "Method": "fileContent",
    "RelativePath": "api/Candidate/fileContent",
    "HttpMethod": "GET",
    "IsController": true,
    "Order": 0,
    "Parameters": [
      {
        "Name": "candidateId",
        "Type": "System.Int32",
        "IsRequired": false
      },
      {
        "Name": "fileType",
        "Type": "System.String",
        "IsRequired": false
      }
    ],
    "ReturnTypes": []
  },
  {
    "ContainingType": "nbRecruitment.Controllers.CandidateController",
    "Method": "fileList",
    "RelativePath": "api/Candidate/fileList",
    "HttpMethod": "POST",
    "IsController": true,
    "Order": 0,
    "Parameters": [
      {
        "Name": "candidateId",
        "Type": "System.String",
        "IsRequired": false
      }
    ],
    "ReturnTypes": []
  },
  {
    "ContainingType": "nbRecruitment.Controllers.CandidateController",
    "Method": "getResumeAndAdmissibility",
    "RelativePath": "api/Candidate/getAdmissibility",
    "HttpMethod": "GET",
    "IsController": true,
    "Order": 0,
    "Parameters": [
      {
        "Name": "candidateId",
        "Type": "System.String",
        "IsRequired": false
      }
    ],
    "ReturnTypes": []
  },
  {
    "ContainingType": "nbRecruitment.Controllers.CandidateController",
    "Method": "getResume",
    "RelativePath": "api/Candidate/getResume",
    "HttpMethod": "GET",
    "IsController": true,
    "Order": 0,
    "Parameters": [
      {
        "Name": "candidateId",
        "Type": "System.Int32",
        "IsRequired": false
      }
    ],
    "ReturnTypes": []
  },
  {
    "ContainingType": "nbRecruitment.Controllers.CandidateController",
    "Method": "jobCandidates",
    "RelativePath": "api/Candidate/jobCandidates",
    "HttpMethod": "POST",
    "IsController": true,
    "Order": 0,
    "Parameters": [
      {
        "Name": "jobCandidatesClass",
        "Type": "nbRecruitment.Controllers.CandidateController\u002BjobCandidatesClass",
        "IsRequired": true
      }
    ],
    "ReturnTypes": []
  },
  {
    "ContainingType": "nbRecruitment.Controllers.CandidateController",
    "Method": "jobCandidates2",
    "RelativePath": "api/Candidate/jobCandidates2",
    "HttpMethod": "POST",
    "IsController": true,
    "Order": 0,
    "Parameters": [
      {
        "Name": "jobCandidatesClass",
        "Type": "nbRecruitment.Controllers.CandidateController\u002BjobCandidatesClass",
        "IsRequired": true
      }
    ],
    "ReturnTypes": []
  },
  {
    "ContainingType": "nbRecruitment.Controllers.CandidateController",
    "Method": "jobCandidatesDialog",
    "RelativePath": "api/Candidate/jobCandidatesDialog",
    "HttpMethod": "POST",
    "IsController": true,
    "Order": 0,
    "Parameters": [
      {
        "Name": "jobCandidatesDialogClass",
        "Type": "nbRecruitment.Controllers.CandidateController\u002BjobCandidatesDialogClass",
        "IsRequired": true
      }
    ],
    "ReturnTypes": []
  },
  {
    "ContainingType": "nbRecruitment.Controllers.CandidateController",
    "Method": "jobCandidatesDialog2",
    "RelativePath": "api/Candidate/jobCandidatesDialog2",
    "HttpMethod": "POST",
    "IsController": true,
    "Order": 0,
    "Parameters": [
      {
        "Name": "jobCandidatesDialogClass",
        "Type": "nbRecruitment.Controllers.CandidateController\u002BjobCandidatesDialogClass",
        "IsRequired": true
      }
    ],
    "ReturnTypes": []
  },
  {
    "ContainingType": "nbRecruitment.Controllers.CandidateController",
    "Method": "jobTypeList",
    "RelativePath": "api/Candidate/jobTypeList",
    "HttpMethod": "GET",
    "IsController": true,
    "Order": 0,
    "Parameters": [],
    "ReturnTypes": []
  },
  {
    "ContainingType": "nbRecruitment.Controllers.CandidateController",
    "Method": "multipleEmailCandidate",
    "RelativePath": "api/Candidate/multipleEmailCandidate",
    "HttpMethod": "POST",
    "IsController": true,
    "Order": 0,
    "Parameters": [
      {
        "Name": "details",
        "Type": "System.String",
        "IsRequired": false
      }
    ],
    "ReturnTypes": []
  },
  {
    "ContainingType": "nbRecruitment.Controllers.CandidateController",
    "Method": "saveJobCandidate",
    "RelativePath": "api/Candidate/saveJobCandidate",
    "HttpMethod": "POST",
    "IsController": true,
    "Order": 0,
    "Parameters": [
      {
        "Name": "saveJobCandidateClass",
        "Type": "nbRecruitment.Controllers.CandidateController\u002BsaveJobCandidateClass",
        "IsRequired": true
      }
    ],
    "ReturnTypes": []
  },
  {
    "ContainingType": "nbRecruitment.Controllers.CandidateController",
    "Method": "transfer",
    "RelativePath": "api/Candidate/transfer",
    "HttpMethod": "POST",
    "IsController": true,
    "Order": 0,
    "Parameters": [
      {
        "Name": "userId",
        "Type": "System.Int32",
        "IsRequired": false
      },
      {
        "Name": "candidateId",
        "Type": "System.Int32",
        "IsRequired": false
      },
      {
        "Name": "transferTo",
        "Type": "System.Int32",
        "IsRequired": false
      }
    ],
    "ReturnTypes": []
  },
  {
    "ContainingType": "nbRecruitment.Controllers.DashboardController",
    "Method": "candidatesProgression",
    "RelativePath": "api/Dashboard/candidatesProgression",
    "HttpMethod": "GET",
    "IsController": true,
    "Order": 0,
    "Parameters": [
      {
        "Name": "userId",
        "Type": "System.Nullable\u00601[[System.Int32, System.Private.CoreLib, Version=8.0.0.0, Culture=neutral, PublicKeyToken=7cec85d7bea7798e]]",
        "IsRequired": false
      },
      {
        "Name": "from",
        "Type": "System.DateTime",
        "IsRequired": false
      },
      {
        "Name": "to",
        "Type": "System.DateTime",
        "IsRequired": false
      }
    ],
    "ReturnTypes": []
  },
  {
    "ContainingType": "nbRecruitment.Controllers.DashboardController",
    "Method": "openPosition",
    "RelativePath": "api/Dashboard/openPosition",
    "HttpMethod": "GET",
    "IsController": true,
    "Order": 0,
    "Parameters": [
      {
        "Name": "userId",
        "Type": "System.Nullable\u00601[[System.Int32, System.Private.CoreLib, Version=8.0.0.0, Culture=neutral, PublicKeyToken=7cec85d7bea7798e]]",
        "IsRequired": false
      },
      {
        "Name": "PostingId",
        "Type": "System.String",
        "IsRequired": false
      }
    ],
    "ReturnTypes": []
  },
  {
    "ContainingType": "nbRecruitment.Controllers.DashboardController",
    "Method": "regCandidates",
    "RelativePath": "api/Dashboard/regCandidates",
    "HttpMethod": "GET",
    "IsController": true,
    "Order": 0,
    "Parameters": [
      {
        "Name": "userId",
        "Type": "System.Nullable\u00601[[System.Int32, System.Private.CoreLib, Version=8.0.0.0, Culture=neutral, PublicKeyToken=7cec85d7bea7798e]]",
        "IsRequired": false
      },
      {
        "Name": "Dates",
        "Type": "System.String",
        "IsRequired": false
      }
    ],
    "ReturnTypes": []
  },
  {
    "ContainingType": "nbRecruitment.Controllers.DashboardController",
    "Method": "test",
    "RelativePath": "api/Dashboard/test",
    "HttpMethod": "GET",
    "IsController": true,
    "Order": 0,
    "Parameters": [],
    "ReturnTypes": []
  },
  {
    "ContainingType": "nbRecruitment.Controllers.ErpController",
    "Method": "candidates",
    "RelativePath": "api/Erp/candidates",
    "HttpMethod": "GET",
    "IsController": true,
    "Order": 0,
    "Parameters": [],
    "ReturnTypes": []
  },
  {
    "ContainingType": "nbRecruitment.Controllers.ErpController",
    "Method": "erpSendEmail",
    "RelativePath": "api/Erp/erpSendEmail",
    "HttpMethod": "POST",
    "IsController": true,
    "Order": 0,
    "Parameters": [
      {
        "Name": "details",
        "Type": "nbRecruitment.Controllers.ErpController\u002Bdetails",
        "IsRequired": true
      }
    ],
    "ReturnTypes": []
  },
  {
    "ContainingType": "nbRecruitment.Controllers.ErpController",
    "Method": "setStatus",
    "RelativePath": "api/Erp/setStatus",
    "HttpMethod": "POST",
    "IsController": true,
    "Order": 0,
    "Parameters": [
      {
        "Name": "candidateId",
        "Type": "System.Int32",
        "IsRequired": false
      }
    ],
    "ReturnTypes": []
  },
  {
    "ContainingType": "nbRecruitment.Controllers.JobController",
    "Method": "addJobType",
    "RelativePath": "api/Job/addJobType",
    "HttpMethod": "POST",
    "IsController": true,
    "Order": 0,
    "Parameters": [
      {
        "Name": "jobtype",
        "Type": "nbRecruitment.Models.Jobtype",
        "IsRequired": true
      }
    ],
    "ReturnTypes": []
  },
  {
    "ContainingType": "nbRecruitment.Controllers.JobController",
    "Method": "editJobType",
    "RelativePath": "api/Job/editJobType",
    "HttpMethod": "POST",
    "IsController": true,
    "Order": 0,
    "Parameters": [
      {
        "Name": "jobtype",
        "Type": "nbRecruitment.Models.Jobtype",
        "IsRequired": true
      }
    ],
    "ReturnTypes": []
  },
  {
    "ContainingType": "nbRecruitment.Controllers.JobController",
    "Method": "jobTypeList",
    "RelativePath": "api/Job/jobTypeList",
    "HttpMethod": "POST",
    "IsController": true,
    "Order": 0,
    "Parameters": [
      {
        "Name": "search",
        "Type": "System.String",
        "IsRequired": false
      },
      {
        "Name": "page",
        "Type": "System.Int32",
        "IsRequired": false
      },
      {
        "Name": "size",
        "Type": "System.Int32",
        "IsRequired": false
      }
    ],
    "ReturnTypes": []
  },
  {
    "ContainingType": "nbRecruitment.Controllers.LanguageController",
    "Method": "addLanguage",
    "RelativePath": "api/Language/addLanguage",
    "HttpMethod": "POST",
    "IsController": true,
    "Order": 0,
    "Parameters": [
      {
        "Name": "language",
        "Type": "nbRecruitment.Models.Language",
        "IsRequired": true
      }
    ],
    "ReturnTypes": []
  },
  {
    "ContainingType": "nbRecruitment.Controllers.LanguageController",
    "Method": "editLanguage",
    "RelativePath": "api/Language/editLanguage",
    "HttpMethod": "POST",
    "IsController": true,
    "Order": 0,
    "Parameters": [
      {
        "Name": "language",
        "Type": "nbRecruitment.Models.Language",
        "IsRequired": true
      }
    ],
    "ReturnTypes": []
  },
  {
    "ContainingType": "nbRecruitment.Controllers.LanguageController",
    "Method": "languageList",
    "RelativePath": "api/Language/languageList",
    "HttpMethod": "POST",
    "IsController": true,
    "Order": 0,
    "Parameters": [
      {
        "Name": "search",
        "Type": "System.String",
        "IsRequired": false
      },
      {
        "Name": "page",
        "Type": "System.Int32",
        "IsRequired": false
      },
      {
        "Name": "size",
        "Type": "System.Int32",
        "IsRequired": false
      }
    ],
    "ReturnTypes": []
  },
  {
    "ContainingType": "nbRecruitment.Controllers.LoginController",
    "Method": "insertEncryption",
    "RelativePath": "api/Login/insertEncryption",
    "HttpMethod": "POST",
    "IsController": true,
    "Order": 0,
    "Parameters": [
      {
        "Name": "password",
        "Type": "System.String",
        "IsRequired": false
      },
      {
        "Name": "id",
        "Type": "System.Int32",
        "IsRequired": false
      }
    ],
    "ReturnTypes": []
  },
  {
    "ContainingType": "nbRecruitment.Controllers.LoginController",
    "Method": "login",
    "RelativePath": "api/Login/login",
    "HttpMethod": "POST",
    "IsController": true,
    "Order": 0,
    "Parameters": [
      {
        "Name": "loggingin",
        "Type": "nbRecruitment.Controllers.LoginController\u002Bloggingin",
        "IsRequired": true
      }
    ],
    "ReturnTypes": []
  },
  {
    "ContainingType": "nbRecruitment.Controllers.MenuController",
    "Method": "userList",
    "RelativePath": "api/Menu/userList",
    "HttpMethod": "POST",
    "IsController": true,
    "Order": 0,
    "Parameters": [
      {
        "Name": "userId",
        "Type": "System.Int32",
        "IsRequired": false
      },
      {
        "Name": "search",
        "Type": "System.String",
        "IsRequired": false
      },
      {
        "Name": "page",
        "Type": "System.Int32",
        "IsRequired": false
      },
      {
        "Name": "size",
        "Type": "System.Int32",
        "IsRequired": false
      }
    ],
    "ReturnTypes": []
  },
  {
    "ContainingType": "nbRecruitment.Controllers.MenuController",
    "Method": "userMenu",
    "RelativePath": "api/Menu/userMenu",
    "HttpMethod": "POST",
    "IsController": true,
    "Order": 0,
    "Parameters": [
      {
        "Name": "userId",
        "Type": "System.Int32",
        "IsRequired": false
      }
    ],
    "ReturnTypes": []
  },
  {
    "ContainingType": "nbRecruitment.Controllers.MenuController",
    "Method": "userMenusSave",
    "RelativePath": "api/Menu/userMenusSave",
    "HttpMethod": "POST",
    "IsController": true,
    "Order": 0,
    "Parameters": [
      {
        "Name": "userId",
        "Type": "System.Int32",
        "IsRequired": false
      },
      {
        "Name": "selectedUserId",
        "Type": "System.Int32",
        "IsRequired": false
      },
      {
        "Name": "selected",
        "Type": "System.String",
        "IsRequired": false
      }
    ],
    "ReturnTypes": []
  },
  {
    "ContainingType": "nbRecruitment.Controllers.NotificationController",
    "Method": "NotificationList",
    "RelativePath": "api/Notification/NotificationList",
    "HttpMethod": "POST",
    "IsController": true,
    "Order": 0,
    "Parameters": [
      {
        "Name": "userId",
        "Type": "System.Int32",
        "IsRequired": false
      }
    ],
    "ReturnTypes": []
  },
  {
    "ContainingType": "nbRecruitment.Controllers.PendingController",
    "Method": "approved",
    "RelativePath": "api/Pending/approved",
    "HttpMethod": "POST",
    "IsController": true,
    "Order": 0,
    "Parameters": [
      {
        "Name": "postingId",
        "Type": "System.Int32",
        "IsRequired": false
      },
      {
        "Name": "isApproved",
        "Type": "System.SByte",
        "IsRequired": false
      }
    ],
    "ReturnTypes": []
  },
  {
    "ContainingType": "nbRecruitment.Controllers.PendingController",
    "Method": "postingList",
    "RelativePath": "api/Pending/postingList",
    "HttpMethod": "POST",
    "IsController": true,
    "Order": 0,
    "Parameters": [
      {
        "Name": "search",
        "Type": "System.String",
        "IsRequired": false
      },
      {
        "Name": "page",
        "Type": "System.Int32",
        "IsRequired": false
      },
      {
        "Name": "size",
        "Type": "System.Int32",
        "IsRequired": false
      }
    ],
    "ReturnTypes": []
  },
  {
    "ContainingType": "nbRecruitment.Controllers.PostController",
    "Method": "addCandidate",
    "RelativePath": "api/Post/addCandidate",
    "HttpMethod": "POST",
    "IsController": true,
    "Order": 0,
    "Parameters": [
      {
        "Name": "ContentType",
        "Type": "System.String",
        "IsRequired": false
      },
      {
        "Name": "ContentDisposition",
        "Type": "System.String",
        "IsRequired": false
      },
      {
        "Name": "Headers",
        "Type": "Microsoft.AspNetCore.Http.IHeaderDictionary",
        "IsRequired": false
      },
      {
        "Name": "Length",
        "Type": "System.Int64",
        "IsRequired": false
      },
      {
        "Name": "Name",
        "Type": "System.String",
        "IsRequired": false
      },
      {
        "Name": "FileName",
        "Type": "System.String",
        "IsRequired": false
      },
      {
        "Name": "admissibility",
        "Type": "System.String",
        "IsRequired": false
      },
      {
        "Name": "posting",
        "Type": "System.String",
        "IsRequired": false
      }
    ],
    "ReturnTypes": []
  },
  {
    "ContainingType": "nbRecruitment.Controllers.PostController",
    "Method": "country",
    "RelativePath": "api/Post/country",
    "HttpMethod": "GET",
    "IsController": true,
    "Order": 0,
    "Parameters": [
      {
        "Name": "postingId",
        "Type": "System.Int32",
        "IsRequired": false
      }
    ],
    "ReturnTypes": []
  },
  {
    "ContainingType": "nbRecruitment.Controllers.PostController",
    "Method": "directPost",
    "RelativePath": "api/Post/directPost",
    "HttpMethod": "GET",
    "IsController": true,
    "Order": 0,
    "Parameters": [
      {
        "Name": "Id",
        "Type": "System.Int32",
        "IsRequired": false
      }
    ],
    "ReturnTypes": []
  },
  {
    "ContainingType": "nbRecruitment.Controllers.PostController",
    "Method": "getDir",
    "RelativePath": "api/Post/getDir",
    "HttpMethod": "GET",
    "IsController": true,
    "Order": 0,
    "Parameters": [
      {
        "Name": "toCombine",
        "Type": "System.String",
        "IsRequired": false
      }
    ],
    "ReturnTypes": []
  },
  {
    "ContainingType": "nbRecruitment.Controllers.PostController",
    "Method": "post",
    "RelativePath": "api/Post/post",
    "HttpMethod": "GET",
    "IsController": true,
    "Order": 0,
    "Parameters": [
      {
        "Name": "search",
        "Type": "System.String",
        "IsRequired": false
      },
      {
        "Name": "page",
        "Type": "System.Int32",
        "IsRequired": false
      },
      {
        "Name": "size",
        "Type": "System.Int32",
        "IsRequired": false
      }
    ],
    "ReturnTypes": []
  },
  {
    "ContainingType": "nbRecruitment.Controllers.PostingController",
    "Method": "AddPosting",
    "RelativePath": "api/Posting/AddPosting",
    "HttpMethod": "POST",
    "IsController": true,
    "Order": 0,
    "Parameters": [
      {
        "Name": "posting",
        "Type": "nbRecruitment.Models.Posting",
        "IsRequired": true
      },
      {
        "Name": "tagUsers",
        "Type": "System.String",
        "IsRequired": false
      }
    ],
    "ReturnTypes": []
  },
  {
    "ContainingType": "nbRecruitment.Controllers.PostingController",
    "Method": "editPosting",
    "RelativePath": "api/Posting/editPosting",
    "HttpMethod": "POST",
    "IsController": true,
    "Order": 0,
    "Parameters": [
      {
        "Name": "newPosting",
        "Type": "nbRecruitment.Models.Posting",
        "IsRequired": true
      },
      {
        "Name": "tagUsers",
        "Type": "System.String",
        "IsRequired": false
      }
    ],
    "ReturnTypes": []
  },
  {
    "ContainingType": "nbRecruitment.Controllers.PostingController",
    "Method": "lanJob",
    "RelativePath": "api/Posting/lanJob",
    "HttpMethod": "GET",
    "IsController": true,
    "Order": 0,
    "Parameters": [],
    "ReturnTypes": []
  },
  {
    "ContainingType": "nbRecruitment.Controllers.PostingController",
    "Method": "lanJobE",
    "RelativePath": "api/Posting/lanJobE",
    "HttpMethod": "GET",
    "IsController": true,
    "Order": 0,
    "Parameters": [
      {
        "Name": "postingId",
        "Type": "System.Int32",
        "IsRequired": false
      }
    ],
    "ReturnTypes": []
  },
  {
    "ContainingType": "nbRecruitment.Controllers.PostingController",
    "Method": "postingList",
    "RelativePath": "api/Posting/postingList",
    "HttpMethod": "POST",
    "IsController": true,
    "Order": 0,
    "Parameters": [
      {
        "Name": "employeeId",
        "Type": "System.Int32",
        "IsRequired": false
      },
      {
        "Name": "search",
        "Type": "System.String",
        "IsRequired": false
      },
      {
        "Name": "page",
        "Type": "System.Int32",
        "IsRequired": false
      },
      {
        "Name": "size",
        "Type": "System.Int32",
        "IsRequired": false
      }
    ],
    "ReturnTypes": []
  },
  {
    "ContainingType": "nbRecruitment.Controllers.ProfileController",
    "Method": "changePassword",
    "RelativePath": "api/Profile/changePassword",
    "HttpMethod": "POST",
    "IsController": true,
    "Order": 0,
    "Parameters": [
      {
        "Name": "userId",
        "Type": "System.Int32",
        "IsRequired": false
      },
      {
        "Name": "currentPassword",
        "Type": "System.String",
        "IsRequired": false
      },
      {
        "Name": "newPassword",
        "Type": "System.String",
        "IsRequired": false
      }
    ],
    "ReturnTypes": []
  },
  {
    "ContainingType": "nbRecruitment.Controllers.ProfileController",
    "Method": "ProfileDetails",
    "RelativePath": "api/Profile/ProfileDetails",
    "HttpMethod": "POST",
    "IsController": true,
    "Order": 0,
    "Parameters": [
      {
        "Name": "classProfileDetails",
        "Type": "nbRecruitment.Controllers.ProfileController\u002BclassProfileDetails",
        "IsRequired": true
      }
    ],
    "ReturnTypes": []
  },
  {
    "ContainingType": "nbRecruitment.Controllers.UploadController",
    "Method": "checkFilesCandidates",
    "RelativePath": "api/Upload/checkFilesCandidates",
    "HttpMethod": "POST",
    "IsController": true,
    "Order": 0,
    "Parameters": [
      {
        "Name": "fileType",
        "Type": "System.String",
        "IsRequired": false
      },
      {
        "Name": "candidateId",
        "Type": "System.String",
        "IsRequired": false
      }
    ],
    "ReturnTypes": []
  },
  {
    "ContainingType": "nbRecruitment.Controllers.UploadController",
    "Method": "uploadFilesCandidates",
    "RelativePath": "api/Upload/uploadFilesCandidates",
    "HttpMethod": "POST",
    "IsController": true,
    "Order": 0,
    "Parameters": [
      {
        "Name": "ContentType",
        "Type": "System.String",
        "IsRequired": false
      },
      {
        "Name": "ContentDisposition",
        "Type": "System.String",
        "IsRequired": false
      },
      {
        "Name": "Headers",
        "Type": "Microsoft.AspNetCore.Http.IHeaderDictionary",
        "IsRequired": false
      },
      {
        "Name": "Length",
        "Type": "System.Int64",
        "IsRequired": false
      },
      {
        "Name": "Name",
        "Type": "System.String",
        "IsRequired": false
      },
      {
        "Name": "FileName",
        "Type": "System.String",
        "IsRequired": false
      },
      {
        "Name": "fileType",
        "Type": "System.String",
        "IsRequired": false
      },
      {
        "Name": "candidateId",
        "Type": "System.String",
        "IsRequired": false
      }
    ],
    "ReturnTypes": []
  },
  {
    "ContainingType": "nbRecruitment.Controllers.UsersController",
    "Method": "addUser",
    "RelativePath": "api/Users/addUser",
    "HttpMethod": "POST",
    "IsController": true,
    "Order": 0,
    "Parameters": [
      {
        "Name": "user",
        "Type": "nbRecruitment.Models.User",
        "IsRequired": true
      },
      {
        "Name": "languages",
        "Type": "System.String",
        "IsRequired": false
      }
    ],
    "ReturnTypes": []
  },
  {
    "ContainingType": "nbRecruitment.Controllers.UsersController",
    "Method": "editUser",
    "RelativePath": "api/Users/editUser",
    "HttpMethod": "POST",
    "IsController": true,
    "Order": 0,
    "Parameters": [
      {
        "Name": "user",
        "Type": "nbRecruitment.Models.User",
        "IsRequired": true
      },
      {
        "Name": "languages",
        "Type": "System.String",
        "IsRequired": false
      }
    ],
    "ReturnTypes": []
  },
  {
    "ContainingType": "nbRecruitment.Controllers.UsersController",
    "Method": "laguageList",
    "RelativePath": "api/Users/laguageList",
    "HttpMethod": "GET",
    "IsController": true,
    "Order": 0,
    "Parameters": [],
    "ReturnTypes": []
  },
  {
    "ContainingType": "nbRecruitment.Controllers.UsersController",
    "Method": "laguageWAsignList",
    "RelativePath": "api/Users/laguageWAsignList",
    "HttpMethod": "GET",
    "IsController": true,
    "Order": 0,
    "Parameters": [
      {
        "Name": "userId",
        "Type": "System.Int32",
        "IsRequired": false
      }
    ],
    "ReturnTypes": []
  },
  {
    "ContainingType": "nbRecruitment.Controllers.UsersController",
    "Method": "userList",
    "RelativePath": "api/Users/userList",
    "HttpMethod": "POST",
    "IsController": true,
    "Order": 0,
    "Parameters": [
      {
        "Name": "userId",
        "Type": "System.Int32",
        "IsRequired": false
      },
      {
        "Name": "search",
        "Type": "System.String",
        "IsRequired": false
      },
      {
        "Name": "page",
        "Type": "System.Int32",
        "IsRequired": false
      },
      {
        "Name": "size",
        "Type": "System.Int32",
        "IsRequired": false
      }
    ],
    "ReturnTypes": []
  },
  {
    "ContainingType": "nbRecruitment.Controllers.WeatherForecastController",
    "Method": "Get",
    "RelativePath": "WeatherForecast",
    "HttpMethod": "GET",
    "IsController": true,
    "Order": 0,
    "Parameters": [],
    "ReturnTypes": [
      {
        "Type": "System.Collections.Generic.IEnumerable\u00601[[nbRecruitment.WeatherForecast, nbRecruitment, Version=1.0.0.0, Culture=neutral, PublicKeyToken=null]]",
        "MediaTypes": [
          "text/plain",
          "application/json",
          "text/json"
        ],
        "StatusCode": 200
      }
    ]
  }
]